highlighter/__init__.py
highlighter/cli.py
highlighter/dom.py
highlighter/highlight.py
highlighter/lexers.py
highlighter/server.py
highlighter/styles.py
bs_highlighter-2.0.3.dist-info/LICENSE
bs_highlighter-2.0.3.dist-info/METADATA
bs_highlighter-2.0.3.dist-info/WHEEL
bs_highlighter-2.0.3.dist-info/entry_points.txt
bs_highlighter-2.0.3.dist-info/top_level.txt
bs_highlighter-2.0.3.dist-info/RECORD
