Metadata-Version: 2.1
Name: bs-highlighter
Version: 2.0.3
Summary: A command-line highlighter syntax-highlighter, using Pygments and widlparser.
Home-page: https://github.com/tabatkins/highlighter
Author: Tab Atkins-Bittner
License: UNKNOWN
Platform: UNKNOWN
Requires-Python: >=3.7
Requires-Dist: pygments (==2.9.0)
Requires-Dist: widlparser (==1.0.11)
